metaschema/__init__.py
metaschema/doc.py
metaschema/indicators.py
metaschema/indicators2.py
metaschema-0.0.3.dist-info/LICENSE
metaschema-0.0.3.dist-info/METADATA
metaschema-0.0.3.dist-info/WHEEL
metaschema-0.0.3.dist-info/RECORD
