Metadata-Version: 2.1
Name: metaschema
Version: 0.0.3
Summary: Repository of Pydantic models for metadata schema.
License: MIT
Author: Aivin V. Solatorio
Author-email: avsolatorio@gmail.com
Requires-Python: >=3.8.1,<4.0.0
Classifier: License :: OSI Approved :: MIT License
Classifier: Programming Language :: Python :: 3
Classifier: Programming Language :: Python :: 3.9
Classifier: Programming Language :: Python :: 3.10
Classifier: Programming Language :: Python :: 3.11
Requires-Dist: datamodel-code-generator (>=0.19.0,<0.20.0)
Requires-Dist: pydantic (>=1.10.5,<2.0.0)
